MANIFEST.in
README.md
setup.py
basstatpl/__init__.py
basstatpl.egg-info/PKG-INFO
basstatpl.egg-info/SOURCES.txt
basstatpl.egg-info/dependency_links.txt
basstatpl.egg-info/requires.txt
basstatpl.egg-info/top_level.txt
basstatpl/core/__init__.py
basstatpl/core/analysis.py
basstatpl/core/group.py
basstatpl/core/simple.py
basstatpl/core/base/__init__.py
basstatpl/core/base/calculations.py
basstatpl/core/util/__init__.py
basstatpl/core/util/tools.py
basstatpl/tests/__init__.py
basstatpl/tests/test_analysis.py
basstatpl/tests/test_group.py
basstatpl/tests/test_simple.py